fssdk/__init__.py
fssdk/_cli.py
fssdk/_protobuf.py
fssdk/_util.py
fssdk/protobuf/__init__.py
fssdk/protobuf/application_pb2.py
fssdk/protobuf/application_pb2.pyi
fssdk/protobuf/desktop_pb2.py
fssdk/protobuf/desktop_pb2.pyi
fssdk/protobuf/flipper_pb2.py
fssdk/protobuf/flipper_pb2.pyi
fssdk/protobuf/gpio_pb2.py
fssdk/protobuf/gpio_pb2.pyi
fssdk/protobuf/gui_pb2.py
fssdk/protobuf/gui_pb2.pyi
fssdk/protobuf/property_pb2.py
fssdk/protobuf/property_pb2.pyi
fssdk/protobuf/storage_pb2.py
fssdk/protobuf/storage_pb2.pyi
fssdk/protobuf/system_pb2.py
fssdk/protobuf/system_pb2.pyi
fssdk-0.1.0a0.dist-info/METADATA
fssdk-0.1.0a0.dist-info/WHEEL
fssdk-0.1.0a0.dist-info/RECORD
